libgoogle/__init__.py
libgoogle/py.typed
rlane_libgoogle-1.0.2.dist-info/METADATA
rlane_libgoogle-1.0.2.dist-info/WHEEL
rlane_libgoogle-1.0.2.dist-info/entry_points.txt
rlane_libgoogle-1.0.2.dist-info/licenses/LICENSE
rlane_libgoogle-1.0.2.dist-info/RECORD
