Metadata-Version: 2.1
Name: rlane-libgoogle
Version: 1.0.2
Summary: Connect to Google Service API's
Keywords: api,client,connect,google,google-api-python-client,google-auth-httplib2,google-auth-oauthlib,httplib2,oauthlib,python,services,xdg
Author-Email: Russel Lane <russel@rlane.com>
License: MIT
Classifier: Development Status :: 4 - Beta
Classifier: Intended Audience :: Developers
Classifier: License :: OSI Approved :: MIT License
Classifier: Programming Language :: Python :: 3
Classifier: Topic :: Software Development :: Libraries :: Python Modules
Project-URL: Homepage, https://github.com/russellane/libgoogle
Requires-Python: >=3.10
Requires-Dist: google-api-python-client>=2.158.0
Requires-Dist: google-auth-httplib2>=0.2.0
Requires-Dist: google-auth-oauthlib>=1.2.1
Requires-Dist: loguru>=0.7.3
Requires-Dist: xdg>=6.0.0
